{
  "generated_at": "2026-07-07T01:31:44",
  "mode": "DRY-RUN (읽기 전용, 주문 없음)",
  "market": {
    "regime": "CAUTION",
    "regime_blind": false,
    "regime_detail": "카나리아 1/2 음전환",
    "day_stance": "CAUTIOUS",
    "day_stance_forced": false,
    "briefing": "오늘 스탠스 신중(CAUTIOUS) · 레짐 CAUTION·신뢰도 31% · 美 오버나이트 neutral(-0.8%) · 고변동(96.0%ile) · 예산 40%·최대 2종목·허용 롱/인버스",
    "blocks_new_buys": false
  },
  "gates": {
    "leverage_dry_run": true,
    "leverage_gate_allowed": false,
    "leverage_gate_reason": "레짐 CAUTION(BULL 아님) → 레버리지 금지"
  },
  "account": {
    "cash": 595323,
    "holdings_readable": "없음/조회실패"
  },
  "holdings_risk": [],
  "entry_candidates": [
    {
      "symbol": "395160",
      "type": "롱",
      "decision": "스킵",
      "breakout": false,
      "ta": -10.8,
      "atr_pct": 8.58,
      "fee_gate_ok": true,
      "why_skip": "미돌파 · TA부족(-11)"
    },
    {
      "symbol": "005930",
      "type": "롱",
      "decision": "스킵",
      "breakout": false,
      "ta": -9.0,
      "atr_pct": 7.46,
      "fee_gate_ok": true,
      "why_skip": "미돌파 · TA부족(-9)"
    },
    {
      "symbol": "000660",
      "type": "롱",
      "decision": "스킵",
      "breakout": false,
      "ta": -12.9,
      "atr_pct": 10.1,
      "fee_gate_ok": true,
      "why_skip": "미돌파 · TA부족(-13)"
    },
    {
      "symbol": "034220",
      "type": "롱",
      "decision": "스킵",
      "breakout": false,
      "ta": -3.1,
      "atr_pct": 7.86,
      "fee_gate_ok": true,
      "why_skip": "미돌파 · TA부족(-3)"
    },
    {
      "symbol": "010140",
      "type": "롱",
      "decision": "스킵",
      "breakout": false,
      "ta": -3.5,
      "atr_pct": 6.64,
      "fee_gate_ok": true,
      "why_skip": "미돌파 · TA부족(-4)"
    },
    {
      "symbol": "011200",
      "type": "롱",
      "decision": "스킵",
      "breakout": false,
      "ta": -9.0,
      "atr_pct": 5.15,
      "fee_gate_ok": true,
      "why_skip": "미돌파 · TA부족(-9)"
    },
    {
      "symbol": "091180",
      "type": "롱",
      "decision": "스킵",
      "breakout": false,
      "ta": -3.8,
      "atr_pct": 5.5,
      "fee_gate_ok": true,
      "why_skip": "미돌파 · TA부족(-4)"
    },
    {
      "symbol": "098560",
      "type": "롱",
      "decision": "평가실패",
      "why_skip": "오류: 일봉 데이터 비어있음"
    },
    {
      "symbol": "117700",
      "type": "롱",
      "decision": "스킵",
      "breakout": false,
      "ta": 12.0,
      "atr_pct": 7.88,
      "fee_gate_ok": true,
      "why_skip": "미돌파"
    },
    {
      "symbol": "114800",
      "type": "인버스",
      "entry_via": "-",
      "decision": "스킵",
      "breakout": false,
      "ta": 19.6,
      "atr_pct": 5.91,
      "fee_gate_ok": true,
      "why_skip": "미돌파 · TA부족(+20<20)"
    }
  ],
  "gap_recovery": {
    "enabled_live": true,
    "now_kst": "01:32",
    "window": "09:00~09:20",
    "candidates": [
      {
        "symbol": "395160",
        "name": "KODEX 미국나스닥100TR",
        "decision": "스킵",
        "gap_open_pct": 0.53,
        "intraday_pct": -4.58,
        "in_window": false,
        "reason": "촉발 없음(오버나이트=normal≠aggressive_buy)"
      },
      {
        "symbol": "005930",
        "name": "삼성전자",
        "decision": "스킵",
        "gap_open_pct": 3.39,
        "intraday_pct": -0.62,
        "in_window": false,
        "reason": "촉발 없음(오버나이트=normal≠aggressive_buy)"
      },
      {
        "symbol": "000660",
        "name": "SK하이닉스",
        "decision": "스킵",
        "gap_open_pct": 1.03,
        "intraday_pct": -4.37,
        "in_window": false,
        "reason": "촉발 없음(오버나이트=normal≠aggressive_buy)"
      },
      {
        "symbol": "034220",
        "name": "LG디스플레이",
        "decision": "스킵",
        "gap_open_pct": 0.27,
        "intraday_pct": -1.98,
        "in_window": false,
        "reason": "촉발 없음(오버나이트=normal≠aggressive_buy)"
      },
      {
        "symbol": "010140",
        "name": "삼성중공업",
        "decision": "스킵",
        "gap_open_pct": 1.28,
        "intraday_pct": -0.42,
        "in_window": false,
        "reason": "촉발 없음(오버나이트=normal≠aggressive_buy)"
      },
      {
        "symbol": "011200",
        "name": "HMM",
        "decision": "스킵",
        "gap_open_pct": 0.52,
        "intraday_pct": 0.57,
        "in_window": false,
        "reason": "촉발 없음(오버나이트=normal≠aggressive_buy)"
      },
      {
        "symbol": "091180",
        "name": "KODEX 자동차",
        "decision": "스킵",
        "gap_open_pct": 0.14,
        "intraday_pct": 3.68,
        "in_window": false,
        "reason": "촉발 없음(오버나이트=normal≠aggressive_buy)"
      },
      {
        "symbol": "098560",
        "name": "KODEX IT",
        "decision": "스킵",
        "gap_open_pct": 0.0,
        "intraday_pct": 0.0,
        "in_window": false,
        "reason": "가격데이터 부족(시가/전일종가 없음)"
      },
      {
        "symbol": "117700",
        "name": "KODEX 철강",
        "decision": "스킵",
        "gap_open_pct": 0.3,
        "intraday_pct": -0.46,
        "in_window": false,
        "reason": "촉발 없음(오버나이트=normal≠aggressive_buy)"
      }
    ]
  },
  "morning_momentum": {
    "enabled_live": true,
    "now_kst": "01:32",
    "window": "09:00~14:00",
    "up_th": 0.6,
    "down_th": 0.6,
    "benchmark": "069500",
    "direction": "none",
    "in_window": false,
    "move_pct": -0.68,
    "intraday_pct": -1.98,
    "would_enter": false,
    "reason": "윈도 밖(01:32∉09:00~14:00)"
  },
  "us_entry_candidates": [
    {
      "symbol": "SPLG",
      "type": "long",
      "decision": "스킵",
      "breakout": false,
      "ta": 4.3,
      "atr_pct": 1.16,
      "why_skip": "미돌파 · TA부족(+4)"
    },
    {
      "symbol": "SCHG",
      "type": "long",
      "decision": "스킵",
      "breakout": true,
      "ta": -2.9,
      "atr_pct": 1.31,
      "why_skip": "TA부족(-3)"
    },
    {
      "symbol": "XLF",
      "type": "long",
      "decision": "스킵",
      "breakout": false,
      "ta": -7.9,
      "atr_pct": 1.27,
      "why_skip": "미돌파 · TA부족(-8)"
    },
    {
      "symbol": "SH",
      "type": "inverse",
      "decision": "스킵",
      "breakout": false,
      "ta": -9.1,
      "atr_pct": 1.07,
      "why_skip": "미돌파 · TA부족(-9)"
    },
    {
      "symbol": "PSQ",
      "type": "inverse",
      "decision": "스킵",
      "breakout": false,
      "ta": 18.2,
      "atr_pct": 1.86,
      "why_skip": "미돌파"
    },
    {
      "symbol": "TLT",
      "type": "defensive",
      "decision": "스킵",
      "breakout": false,
      "ta": -0.9,
      "atr_pct": 0.51,
      "why_skip": "미돌파 · TA부족(-1) · 수수료게이트"
    },
    {
      "symbol": "SHY",
      "type": "defensive",
      "decision": "스킵",
      "breakout": false,
      "ta": 17.1,
      "atr_pct": 0.08,
      "why_skip": "미돌파 · 수수료게이트"
    }
  ],
  "us_summary": {
    "would_buy": []
  },
  "summary": {
    "would_buy": [],
    "would_sell": [],
    "new_buys_blocked_by_stance": false,
    "verdict": "진입 조건 미충족 — 현금/방어 유지"
  }
}